README
setup.py
stripeol/__init__.py
stripeol/cli.py
stripeol/detect.py
stripeol/stripeol.py
stripeol.egg-info/PKG-INFO
stripeol.egg-info/SOURCES.txt
stripeol.egg-info/dependency_links.txt
stripeol.egg-info/entry_points.txt
stripeol.egg-info/top_level.txt